datatune/__init__.py
datatune/agent/__init__.py
datatune/agent/agent.py
datatune/agent/runtime.py
datatune/core/constants.py
datatune/core/filter.py
datatune/core/map.py
datatune/core/op.py
datatune/llm/__init__.py
datatune/llm/batch_utils.py
datatune/llm/llm.py
datatune/llm/model_rate_limits.py
datatune-0.0.4.dist-info/licenses/LICENSE
datatune-0.0.4.dist-info/METADATA
datatune-0.0.4.dist-info/WHEEL
datatune-0.0.4.dist-info/top_level.txt
datatune-0.0.4.dist-info/RECORD
