Metadata-Version: 2.4
Name: datatune
Version: 0.0.4
Summary: Your backend for LLM powered Big Data Apps
Author-email: Abhijith Neil Abraham <abhijith@vitalops.ai>, Fariz Rahman <fariz@vitalops.ai>
License: MIT
Project-URL: Homepage, https://github.com/vitalops/datatune
Project-URL: Bug Tracker, https://github.com/vitalops/datatune/issues
Requires-Python: >=3.8
License-File: LICENSE
Requires-Dist: numpy
Requires-Dist: litellm
Requires-Dist: dask[dataframe]
Requires-Dist: pandas
Dynamic: license-file
